__init__.py
cases_management.py
config.py
enums.py
jelver.py
local_tests.py
remote_tests.py
utils/__init__.py
utils/api.py
utils/jelver_exceptions.py
utils/pillow_utils.py
utils/playwright_utils.py
utils/render.py
jelver_cli-1.0.25.dist-info/LICENCE
jelver_cli-1.0.25.dist-info/METADATA
jelver_cli-1.0.25.dist-info/WHEEL
jelver_cli-1.0.25.dist-info/entry_points.txt
jelver_cli-1.0.25.dist-info/top_level.txt
jelver_cli-1.0.25.dist-info/RECORD
