Metadata-Version: 2.1
Name: jelver-cli
Version: 1.0.25
Summary: Jelver CLI is a command line interface for Jelver. It allows you to interact with Jelver to conduct end to end frontend testing from the terminal.
Author-email: Jelver dev team <info@jelver.com>
Classifier: Programming Language :: Python :: 3
Classifier: License :: OSI Approved :: MIT License
Classifier: Operating System :: OS Independent
Requires-Python: >=3.8
License-File: LICENCE
Requires-Dist: requests
Requires-Dist: emoji
Requires-Dist: colorama
Requires-Dist: tqdm
Requires-Dist: tabulate
Requires-Dist: docopt
Requires-Dist: Pillow
Requires-Dist: playwright
